{
 "_typename": "TMap",
 "name": "",
 "arr": [
  {
   "_typename": "TPair",
   "first": {
    "_typename": "TObjString",
    "fUniqueID": 0,
    "fBits": 50331648,
    "fString": "Str4"
   },
   "second": {
    "_typename": "TNamed",
    "fUniqueID": 0,
    "fBits": 50331648,
    "fName": "Name4",
    "fTitle": "Title4"
   }
  },
  {
   "_typename": "TPair",
   "first": {
    "_typename": "TObjString",
    "fUniqueID": 0,
    "fBits": 50331648,
    "fString": "Str5"
   },
   "second": {
    "_typename": "TNamed",
    "fUniqueID": 0,
    "fBits": 50331648,
    "fName": "Name5",
    "fTitle": "Title5"
   }
  },
  {
   "_typename": "TPair",
   "first": {
    "_typename": "TObjString",
    "fUniqueID": 0,
    "fBits": 50331648,
    "fString": "Str6"
   },
   "second": {
    "_typename": "TNamed",
    "fUniqueID": 0,
    "fBits": 50331648,
    "fName": "Name6",
    "fTitle": "Title6"
   }
  },
  {
   "_typename": "TPair",
   "first": {
    "_typename": "TObjString",
    "fUniqueID": 0,
    "fBits": 50331648,
    "fString": "Str7"
   },
   "second": {
    "_typename": "TNamed",
    "fUniqueID": 0,
    "fBits": 50331648,
    "fName": "Name7",
    "fTitle": "Title7"
   }
  },
  {
   "_typename": "TPair",
   "first": {
    "_typename": "TObjString",
    "fUniqueID": 0,
    "fBits": 50331648,
    "fString": "Str8"
   },
   "second": {
    "_typename": "TNamed",
    "fUniqueID": 0,
    "fBits": 50331648,
    "fName": "Name8",
    "fTitle": "Title8"
   }
  },
  {
   "_typename": "TPair",
   "first": {
    "_typename": "TObjString",
    "fUniqueID": 0,
    "fBits": 50331648,
    "fString": "Str9"
   },
   "second": {
    "_typename": "TNamed",
    "fUniqueID": 0,
    "fBits": 50331648,
    "fName": "Name9",
    "fTitle": "Title9"
   }
  },
  {
   "_typename": "TPair",
   "first": {
    "_typename": "TObjString",
    "fUniqueID": 0,
    "fBits": 50331648,
    "fString": "Str0"
   },
   "second": {
    "_typename": "TNamed",
    "fUniqueID": 0,
    "fBits": 50331648,
    "fName": "Name0",
    "fTitle": "Title0"
   }
  },
  {
   "_typename": "TPair",
   "first": {
    "_typename": "TObjString",
    "fUniqueID": 0,
    "fBits": 50331648,
    "fString": "Str1"
   },
   "second": {
    "_typename": "TNamed",
    "fUniqueID": 0,
    "fBits": 50331648,
    "fName": "Name1",
    "fTitle": "Title1"
   }
  },
  {
   "_typename": "TPair",
   "first": {
    "_typename": "TObjString",
    "fUniqueID": 0,
    "fBits": 50331648,
    "fString": "Str2"
   },
   "second": {
    "_typename": "TNamed",
    "fUniqueID": 0,
    "fBits": 50331648,
    "fName": "Name2",
    "fTitle": "Title2"
   }
  },
  {
   "_typename": "TPair",
   "first": {
    "_typename": "TObjString",
    "fUniqueID": 0,
    "fBits": 50331648,
    "fString": "Str3"
   },
   "second": {
    "_typename": "TNamed",
    "fUniqueID": 0,
    "fBits": 50331648,
    "fName": "Name3",
    "fTitle": "Title3"
   }
  }
 ],
 "fUniqueID": 0,
 "fBits": 50331648
}